ask_docs/__init__.py
ask_docs/config.py
ask_docs/main.py
ask_docs/cli/__init__.py
ask_docs/cli/main.py
ask_docs/core/__init__.py
ask_docs/core/document_retrieval.py
ask_docs/core/prompt_builder.py
ask_docs/core/query_processor.py
ask_docs/llm/__init__.py
ask_docs/llm/anthropic_llm.py
ask_docs/llm/base.py
ask_docs/llm/gemini_llm.py
ask_docs/llm/groq_llm.py
ask_docs/llm/ollama_llm.py
ask_docs/llm/openai_llm.py
ask_docs/tui/__init__.py
ask_docs/tui/app.py
ask_docs/tui/style.css
ask_docs/web/__init__.py
ask_docs/web/app.py
ask_docs/web/handlers.py
ask_docs/web/static/.gitkeep
ask_docs/web/templates/index.html
ask_docs/web/templates/kb_status.html
ask_docs/web/templates/model_info.html
ask_docs/web/templates/templates.html
ask_docs-0.1.4.dist-info/licenses/LICENSE
ask_docs-0.1.4.dist-info/METADATA
ask_docs-0.1.4.dist-info/WHEEL
ask_docs-0.1.4.dist-info/entry_points.txt
ask_docs-0.1.4.dist-info/top_level.txt
ask_docs-0.1.4.dist-info/RECORD
