Metadata-Version: 2.4
Name: ask-docs
Version: 0.1.4
Summary: CLI and web assistant for document collections using LLMs and RAG
Author-email: Michael Borck <michael@borck.me>
License-Expression: MIT
Keywords: rag,llm,assistant,cli,web,documentation,chat,knowledge-base
Classifier: Development Status :: 4 - Beta
Classifier: Environment :: Console
Classifier: Intended Audience :: Developers
Classifier: Intended Audience :: End Users/Desktop
Classifier: Programming Language :: Python :: 3
Classifier: Programming Language :: Python :: 3.9
Classifier: Programming Language :: Python :: 3.10
Classifier: Programming Language :: Python :: 3.11
Classifier: Topic :: Documentation
Classifier: Topic :: Text Processing :: Markup
Requires-Python: >=3.9
License-File: LICENSE
Requires-Dist: typer[all]
Requires-Dist: rich
Requires-Dist: openai
Requires-Dist: requests
Requires-Dist: anthropic
Requires-Dist: google-generativeai
Requires-Dist: groq
Requires-Dist: python-fasthtml
Requires-Dist: python-dotenv
Requires-Dist: textual>=0.52.1
Provides-Extra: dev
Requires-Dist: pytest; extra == "dev"
Requires-Dist: pytest-cov; extra == "dev"
Requires-Dist: ruff; extra == "dev"
Requires-Dist: mypy; extra == "dev"
Requires-Dist: twine==6.0.1; extra == "dev"
Provides-Extra: embeddings
Requires-Dist: numpy; extra == "embeddings"
Requires-Dist: sentence-transformers; extra == "embeddings"
Provides-Extra: full
Requires-Dist: numpy; extra == "full"
Requires-Dist: sentence-transformers; extra == "full"
Requires-Dist: pytest; extra == "full"
Requires-Dist: pytest-cov; extra == "full"
Requires-Dist: ruff; extra == "full"
Requires-Dist: mypy; extra == "full"
Requires-Dist: twine==6.0.1; extra == "full"
Dynamic: license-file
